minimailer/__init__.py
minimailer/app.py
minimailer/csv.py
minimailer-0.0.3.dist-info/LICENSE
minimailer-0.0.3.dist-info/METADATA
minimailer-0.0.3.dist-info/WHEEL
minimailer-0.0.3.dist-info/entry_points.txt
minimailer-0.0.3.dist-info/top_level.txt
minimailer-0.0.3.dist-info/RECORD
