Metadata-Version: 2.1
Name: minimailer
Version: 0.0.3
Summary: Send automated emails using a CSV datafile and a template
Home-page: https://gitlab.torproject.org/rhatto/minimailer
Author: Silvio Rhatto
Author-email: rhatto@torproject.org
License: GPLv3
Classifier: Development Status :: 3 - Alpha
Classifier: Environment :: Console
Classifier: Intended Audience :: Developers
Classifier: Intended Audience :: Information Technology
Classifier: Intended Audience :: System Administrators
Classifier: License :: OSI Approved :: GNU General Public License v3 or later (GPLv3+)
Classifier: Natural Language :: English
Classifier: Programming Language :: Python
Classifier: Programming Language :: Python :: 3 :: Only
Classifier: Programming Language :: Python :: 3
Classifier: Programming Language :: Python :: 3.9
Classifier: Topic :: Communications :: Email
Classifier: Topic :: Communications :: Email :: Mailing List Servers
License-File: LICENSE
Requires-Dist: importlib-metadata ; python_version < "3.8"
